{
  "cli": {
    "version": ">= 18.4.0",
    "appVersionSource": "remote"
  },
  "build": {
    "development": {
      "developmentClient": true,
      "distribution": "internal",
      "env": {
        "EXPO_PUBLIC_API_URL": "https://api.dandelionz.com.ng"
      }
    },
    "preview": {
      "distribution": "internal",
      "env": {
        "EXPO_PUBLIC_API_URL": "https://api.dandelionz.com.ng"
      }
    },
    "production": {
      "autoIncrement": true,
      "env": {
        "EXPO_PUBLIC_API_URL": "https://api.dandelionz.com.ng"
      }
    }
  },
  "submit": {
    "production": {}
  }
}
